LICENSE
README.md
setup.py
database_json.egg-info/PKG-INFO
database_json.egg-info/SOURCES.txt
database_json.egg-info/dependency_links.txt
database_json.egg-info/top_level.txt
json_database/__init__.py
json_database/json_db.py
json_database/json_db_exceptions.py