Metadata-Version: 2.1
Name: database-json
Version: 0.0.2
Summary: This module for create database with JSON
Home-page: https://github.com/hleb2702/json_db.git
Download-URL: https://github.com/hleb2702/json_db/archive/refs/heads/main.zip
Author: Hleb2702
Author-email: glebstetko2@gmail.com
License: Apache License, Version 2.0, see LICENSE file
Requires: json
License-File: LICENSE
